Workbook

Sheet README
A1: GOLFIN Economy Model
A2: Built 2026-08-19 from the live repo/backend values (post-÷10 rebalance of 2026-08-12).
A3: Replaces the outdated 'New levels.xlsx' Ken's AI reviewed (its values were pre-÷10 and pre-cutover).
A5: Legend
A6: Blue text | B6: editable assumption / scenario lever
A7: Black text | B7: formula — recalculates
A8: Yellow fill | B8: key assumption to review
A10: Sources of record
A11: Earn actions & values | B11: playlife game_point_actions catalog + Slice 2 rebalance (RP_REBALANCE.md)
A12: Level-up costs | B12: Assets/Data/LevelUpCosts.csv (240 rows, cost_r = ceil(level/2))
A13: Shop / stamina / prizes / gacha | B13: Assets/Resources/Data/*.csv
A14: Policy layer | B14: ECONOMY_MASTER.md (same folder) — the Ken-facing document

Sheet Sources
A1: RP EARN ACTIONS (server catalog game_point_actions — the ONLY ways RP enters)
A2: Action | B2: RP | C2: Cadence / cap | D2: Note
A3: hole_complete | B3: 10 | C3: per hole finished | D3: core loop earn
A4: hole_replay | B4: 5 | C4: per replayed hole | D4: reduced pool on replays
A5: versus_win | B5: 20 | C5: per 1v1 win | D5: modes.csv reward1Amount
A6: tournament_prize | B6: per prize band | C6: cap 2,000 per event | D6: granted at resolve via earn_pts_v2
A7: GPS visit verification | B7: 10–50 | C7: per verified visit | D7: partner-app earn, shared ledger; never ranks on leaderboards
A8: admin grant | B8: manual | C8: dashboard | D8: ops only; never ranks
A10: DAILY EARN SCENARIO (edit blue)
A11: Holes finished / day | B11: 18
A12: Replays / day | B12: 6
A13: 1v1 wins / day | B13: 3
A14: GPS visits / day (avg 30 RP) | B14: 1
A15: Daily RP earned | B15: =B11*10+B12*5+B13*20+B14*30 -> 300
A17: DAILY RECURRING SPEND (edit blue — LIVE sinks only)
A18: Practice rounds / day (x10 RP) | B18: 2
A19: Tournament entries / day (avg fee) | B19: 10
A20: Stamina boosts / day (avg 20 RP) | B20: 1
A21: Daily RP spent (recurring) | B21: =B18*10+B19+B20*20 -> 50
A22: NET daily RP (funds level-ups & purchases) | B22: =B15-B21 -> 250

Sheet Sinks
A1: RP SINKS (live values)
A2: Sink | B2: RP | C2: Status | D2: Note
A3: Practice entry fee | B3: 10 | C3: LIVE | D3: modes.csv
A4: Tournament entry fee | B4: 0 / 10 / 50 | C4: LIVE | D4: per tournament (admin-set); debited server-side pre-entry
A5: Character/club level-up | B5: ceil(level/2) per level | C5: LIVE | D5: LevelUpCosts.csv — see Progression tab
A6: Shop: clubs | B6: 100–600 (sale 80–600) | C6: LIVE | D6: shop_catalog.csv, 7 legacy clubs today; roster pricing → ClubEconomy tab
A7: Stamina shop items | B7: 12–31 | C7: LIVE | D7: ShopTransaction→PointsSpendGate (spend reason stamina_boost); tournament stamina ISOLATED per tournament (Cesar [d])
A8: Shop: balls | B8: 50 (sale 35) | C8: DORMANT | D8: balls stack as quantity (BallData) but NO consumption on play exists — one-time buys, not recurring
A9: Repairs (durability) | B9: RepairKit items | C9: DORMANT | D9: UseBestRepairKit restores durability, but NOTHING in gameplay ever decreases currentDurability — wear is unimplemented
A10: Gacha x1 / x10 | B10: 50–75 / 450–675 | C10: DORMANT | D10: gacha_banners.csv — prize pool is a STATIC MOCK (GachaMockPrizePool.cs), no real ticket spend
A12: ⚠ Only entry fees, level-ups and stamina boosts recur as live sinks today. Repairs, ball consumption and gacha are DESIGNED sinks awaiting mechanics — the economy currently leaks upward once a player caps their roster.

Sheet LevelUpCosts
A1: level | B1: cost_r | C1: sp_reward
A2: 1 | B2: 1 | C2: 1
A3: 2 | B3: 1 | C3: 1
A4: 3 | B4: 2 | C4: 1
A5: 4 | B5: 2 | C5: 1
A6: 5 | B6: 3 | C6: 1
A7: 6 | B7: 3 | C7: 1
A8: 7 | B8: 4 | C8: 1
A9: 8 | B9: 4 | C9: 1
A10: 9 | B10: 5 | C10: 1
A11: 10 | B11: 5 | C11: 1
A12: 11 | B12: 6 | C12: 1
A13: 12 | B13: 6 | C13: 1
... A241: 240 | B241: 120 | C241: 1

Sheet Progression
A1: CHARACTER/CLUB PROGRESSION COST (from LevelUpCosts tab — formulas)
A2: Tier | B2: Levels | C2: RP cost for tier (SUMIFS) | D2: Cumulative RP | E2: Days at daily earn
A3: Common | B3: 10–39 | C3: =SUMIFS(LevelUpCosts!B:B,LevelUpCosts!A:A,">=10",LevelUpCosts!A:A,"<=39") -> 375 | D3: =SUMIFS(LevelUpCosts!B:B,LevelUpCosts!A:A,"<=39") -> 400 | E3: =D3/Sources!B22 -> 1.6
A4: Uncommon | B4: 40–79 | C4: =SUMIFS(LevelUpCosts!B:B,LevelUpCosts!A:A,">=40",LevelUpCosts!A:A,"<=79") -> 1200 | D4: =SUMIFS(LevelUpCosts!B:B,LevelUpCosts!A:A,"<=79") -> 1600 | E4: =D4/Sources!B22 -> 6.4
A5: Rare | B5: 80–119 | C5: =SUMIFS(LevelUpCosts!B:B,LevelUpCosts!A:A,">=80",LevelUpCosts!A:A,"<=119") -> 2000 | D5: =SUMIFS(LevelUpCosts!B:B,LevelUpCosts!A:A,"<=119") -> 3600 | E5: =D5/Sources!B22 -> 14.4
A6: Mythic | B6: 120–159 | C6: =SUMIFS(LevelUpCosts!B:B,LevelUpCosts!A:A,">=120",LevelUpCosts!A:A,"<=159") -> 2800 | D6: =SUMIFS(LevelUpCosts!B:B,LevelUpCosts!A:A,"<=159") -> 6400 | E6: =D6/Sources!B22 -> 25.6
A7: Legendary | B7: 160–199 | C7: =SUMIFS(LevelUpCosts!B:B,LevelUpCosts!A:A,">=160",LevelUpCosts!A:A,"<=199") -> 3600 | D7: =SUMIFS(LevelUpCosts!B:B,LevelUpCosts!A:A,"<=199") -> 10000 | E7: =D7/Sources!B22 -> 40
A8: Supreme | B8: 200–239 | C8: =SUMIFS(LevelUpCosts!B:B,LevelUpCosts!A:A,">=200",LevelUpCosts!A:A,"<=239") -> 4400 | D8: =SUMIFS(LevelUpCosts!B:B,LevelUpCosts!A:A,"<=239") -> 14400 | E8: =D8/Sources!B22 -> 57.6
A9: TOTAL (levels 1–240) | C9: =SUM(C3:C8) -> 14375 | D9: =SUMIFS(LevelUpCosts!B:B,LevelUpCosts!A:A,"<=240") -> 14520 | E9: =D9/Sources!B22 -> 58.08
A11: Note: levels 1–9 precede the Common band (starting levels are 10/40/80/120/160/200 per rarity); their cost is included in TOTAL.

Sheet ClubEconomy
A1: CLUB ROSTER ECONOMY (C2 roster: 799 clubs = 19 brands x 7 types x 6 rarities + 7 legacy)
A2: Rarity | B2: Proposed shop RP (edit) | C2: Days to afford | D2: Clubs at this rarity | E2: Note
A3: Common | B3: 100 | C3: =B3/Sources!B22 -> 0.4 | D3: 133
A4: Uncommon | B4: 200 | C4: =B4/Sources!B22 -> 0.8 | D4: 133
A5: Rare | B5: 400 | C5: =B5/Sources!B22 -> 1.6 | D5: 133
A6: Mythic | B6: 800 | C6: =B6/Sources!B22 -> 3.2 | D6: 133
A7: Legendary | B7: 1500 | C7: =B7/Sources!B22 -> 6 | D7: 133
A8: Supreme | B8: 3000 | C8: =B8/Sources!B22 -> 12 | D8: 133
A10: Anchors: legacy shop prices 100–600 RP; agreed rule — rarity acquired with RP ONLY, never money (Cesar [i]).
A11: Recommendation: shop stocks a rotating subset; Supreme optionally earn-only (tournament prizes) to keep scarcity.

Sheet Tournaments
A1: PRIZE TABLES (tournament_prizes.csv) — pool math by formula
A2: Table | B2: From | C2: To | D2: RP | E2: Places (=To-From+1) | F2: Band total (=RP*Places)
A3: prize_small | B3: 1 | C3: 1 | D3: 300 | E3: =C3-B3+1 -> 1 | F3: =D3*E3 -> 300
A4: prize_small | B4: 2 | C4: 3 | D4: 150 | E4: =C4-B4+1 -> 2 | F4: =D4*E4 -> 300
A5: prize_small | B5: 4 | C5: 10 | D5: 50 | E5: =C5-B5+1 -> 7 | F5: =D5*E5 -> 350
A6: prize_medium | B6: 1 | C6: 1 | D6: 500 | E6: =C6-B6+1 -> 1 | F6: =D6*E6 -> 500
A7: prize_medium | B7: 2 | C7: 3 | D7: 300 | E7: =C7-B7+1 -> 2 | F7: =D7*E7 -> 600
A8: prize_medium | B8: 4 | C8: 10 | D8: 100 | E8: =C8-B8+1 -> 7 | F8: =D8*E8 -> 700
A9: prize_major | B9: 1 | C9: 1 | D9: 2000 | E9: =C9-B9+1 -> 1 | F9: =D9*E9 -> 2000
A10: prize_major | B10: 2 | C10: 3 | D10: 1200 | E10: =C10-B10+1 -> 2 | F10: =D10*E10 -> 2400
A11: prize_major | B11: 4 | C11: 10 | D11: 500 | E11: =C11-B11+1 -> 7 | F11: =D11*E11 -> 3500
A12: prize_major | B12: 11 | C12: 50 | D12: 100 | E12: =C12-B12+1 -> 40 | F12: =D12*E12 -> 4000
A14: Pool totals
A15: prize_small | F15: =SUMIFS(F3:F12,A3:A12,"prize_small") -> 950
A16: prize_medium | F16: =SUMIFS(F3:F12,A3:A12,"prize_medium") -> 1800
A17: prize_major | F17: =SUMIFS(F3:F12,A3:A12,"prize_major") -> 11900
A18: Cap check: max single band RP | D18: =MAX(D3:D12) -> 2000 | E18: server cap 2,000/event | F18: =IF(D18<=2000,"OK","OVER CAP") -> OK

Sheet PaidTrack
A1: PAID (REAL-MONEY) TRACK — POLICY, NOT IMPLEMENTATION
A2: Current state: NOTHING is sold for real money. RP cannot be purchased. (Cesar [a][g], live code verified.)
A3: Standing rule (agreed Ken/Cesar): no pay-to-win. Rarity/progression acquired with RP only. (Cesar [i])
A4: Never sold: rarity items for money; RP/XP/materials; stamina recovery for money; repairs for paid currency;
A5: stat-carrying skins; tournament slots/priority; RP cash-out (sponsor prize exchange only).
A6: Sellable when real cosmetics EXIST (3D avatars / club skins — none yet): skins/cosmetics with zero stats,
A7: emotes/effects/spectator features, season pass with cosmetic+title rewards only.
A8: Gate: the paid track opens only after cosmetic CONTENT ships; it is a content problem, not an economy problem.
A9: B2B (not user payments): golf-course subscriptions, sponsor campaigns — split 50% rewards / 40% GOLFIN / 10% host course.
